characters_sn/__init__.py
characters_sn/ch.py
characters_sn-0.0.3.dist-info/LICENSE
characters_sn-0.0.3.dist-info/WHEEL
characters_sn-0.0.3.dist-info/METADATA
characters_sn-0.0.3.dist-info/RECORD
