Metadata-Version: 2.1
Name: characters-sn
Version: 0.0.3
Summary: functions to calculate group characters of S_n.
License: MIT
Author: Vladislav Kargin
Author-email: slavakargin@yahoo.com
Requires-Python: >=3.7,<4.0
Classifier: License :: OSI Approved :: MIT License
Classifier: Programming Language :: Python :: 3
Classifier: Programming Language :: Python :: 3.7
Classifier: Programming Language :: Python :: 3.8
Classifier: Programming Language :: Python :: 3.9
